CHANGES.txt
README.txt
bootstrap.py
buildout.cfg
setup.py
src/zope/__init__.py
src/zope.thread.egg-info/PKG-INFO
src/zope.thread.egg-info/SOURCES.txt
src/zope.thread.egg-info/dependency_links.txt
src/zope.thread.egg-info/namespace_packages.txt
src/zope.thread.egg-info/not-zip-safe
src/zope.thread.egg-info/top_level.txt
src/zope/thread/SETUP.cfg
src/zope/thread/__init__.py
src/zope/thread/_zope_thread.c
src/zope/thread/tests.py
