Metadata-Version: 1.0
Name: zope.thread
Version: 3.4dev-r73086
Summary: Zope3 Thread-Local Storage
Home-page: http://svn.zope.org/zope.thread
Author: Zope Corporation and Contributors
Author-email: zope3-dev@zope.org
License: ZPL 2.1
Platform: UNKNOWN
